openalpha/__init__.py
openalpha/evaluator.py
openalpha/util.py
openalpha-0.1.5.dist-info/LICENSE
openalpha-0.1.5.dist-info/METADATA
openalpha-0.1.5.dist-info/WHEEL
openalpha-0.1.5.dist-info/top_level.txt
openalpha-0.1.5.dist-info/RECORD
