Metadata-Version: 2.2
Name: openalpha
Version: 0.1.5
Summary: OpenAlpha Utils
Author-email: OpenAlpha <contact@openalpha.net>
Project-URL: Homepage, https://github.com/june-nahmgoong/openalpha
Project-URL: Issues, https://github.com/june-nahmgoong/openalpha/issues
Classifier: Programming Language :: Python :: 3
Classifier: License :: OSI Approved :: MIT License
Classifier: Operating System :: OS Independent
Requires-Python: >=3.8
License-File: LICENSE
Requires-Dist: numpy
Requires-Dist: pandas
Requires-Dist: tqdm
Requires-Dist: google-cloud-storage
